{
    "walletActivity": {
        "all": {
            "english": "All",
            "german": "Alle",
            "japanese": "すべて",
            "korean": "모두",
            "mandarin": "所有",
            "spanish": "Todas"
        },
        "allTransactions": {
            "english": "All Transactions",
            "german": "Alle Transaktionen",
            "japanese": "すべての取り引き",
            "korean": "모든 트랜잭션",
            "mandarin": "所有交易",
            "spanish": "Todas las transacciones"
        },
        "amount": {
            "english": "Amount",
            "german": "Menge",
            "japanese": "量",
            "korean": "양",
            "mandarin": "量",
            "spanish": "Cantidad"
        },
        "approved": {
            "english": "Approved",
            "german": "Genehmigt",
            "japanese": "承認済み",
            "korean": "승인",
            "mandarin": "已批准",
            "spanish": "Aprobado"
        },
        "cancelButton": {
            "english": "Cancel Transaction",
            "german": "Transaktion abbrechen",
            "japanese": "トランザクションのキャンセル",
            "korean": "트랜잭션 취소",
            "mandarin": "取消交易",
            "spanish": "Cancelar transacción"
        },
        "cancelButtonTooltip": {
            "english": "Canceling this Transaction will cost",
            "german": "Die Stornierung dieser Transaktion kostet Transaction",
            "japanese": "この取引をキャンセルすると費用がかかります",
            "korean": "이 트랜잭션을 취소하면 비용이 발생합니다.",
            "mandarin": "取消此交易将花费",
            "spanish": "Cancelar esta transacción costará"
        },
        "cancelButtonTooltipDisabled": {
            "english": "Transaction can be cancelled only after",
            "german": "Die Transaktion kann erst nach storniert werden",
            "japanese": "取引はその後にのみキャンセルできます",
            "korean": "이후에야 트랜잭션을 취소할 수 있습니다.",
            "mandarin": "交易完成后才能取消",
            "spanish": "La transacción se puede cancelar solo después de"
        },
        "cancelDate": {
            "english": "Cancellation initiated on",
            "german": "Kündigung eingeleitet am",
            "japanese": "キャンセルが開始されました",
            "korean": "취소 시작 날짜",
            "mandarin": "取消开始于",
            "spanish": "Cancelación iniciada el"
        },
        "cancelled": {
            "english": "Cancelled",
            "german": "Abgesagt",
            "japanese": "キャンセル",
            "korean": "취소",
            "mandarin": "取消",
            "spanish": "Cancelado"
        },
        "cancelling": {
            "english": "Cancelling",
            "german": "Stornieren",
            "japanese": "キャンセル",
            "korean": "취소",
            "mandarin": "取消",
            "spanish": "Cancelado"
        },
        "cancelModalClose": {
            "english": "Close",
            "german": "Schließen",
            "japanese": "閉じる",
            "korean": "닫기",
            "mandarin": "关闭",
            "spanish": "Cerca"
        },
        "cancelModalConfirm": {
            "english": "Confirm",
            "german": "Bestätigen",
            "japanese": "確認",
            "korean": "확인",
            "mandarin": "确认",
            "spanish": "Confirmar"
        },
        "cancelModalDesc": {
            "english": "I confirm that this request would incur a transaction fee of ",
            "german": "Ich bestätige, dass für diese Anfrage eine Transaktionsgebühr von . anfallen würde",
            "japanese": "このリクエストには、以下の取引手数料がかかることを確認します",
            "korean": "본인은 이 요청에 트랜잭션 수수료가 부과됨을 확인합니다.",
            "mandarin": "我确认此请求将产生交易费用",
            "spanish": "Confirmo que esta solicitud incurriría en una tarifa de transacción de"
        },
        "cancelModalNote": {
            "english": "No transaction fees will be charged.",
            "german": "Es werden keine Transaktionsgebühren erhoben.",
            "japanese": "取引手数料はかかりません。",
            "korean": "트랜잭션 수수료는 부과되지 않습니다.",
            "mandarin": "不会收取任何交易费用。",
            "spanish": "No serán agregados costos por transacción."
        },
        "cancelModalTitle": {
            "english": "Cancellation status",
            "german": "Stornierungsstatus",
            "japanese": "キャンセル状況",
            "korean": "취소 상태",
            "mandarin": "取消状态",
            "spanish": "Estado de cancelación"
        },
        "cancelModalUnsuccessful": {
            "english": "unsuccessful",
            "german": "erfolglos",
            "japanese": "失敗しました",
            "korean": "실패",
            "mandarin": "不成功",
            "spanish": "fracasado"
        },
        "contractDeployment": {
            "english": "Contract Deployment",
            "german": "Vertragsbereitstellung",
            "japanese": "契約の展開",
            "korean": "컨트랙트 배포",
            "mandarin": "合同部署",
            "spanish": "Despliegue de contrato"
        },
        "contractInteraction": {
            "english": "Contract Interaction",
            "german": "Vertragsinteraktion",
            "japanese": "契約の相互作用",
            "korean": "컨트랙트 인터랙션",
            "mandarin": "合约互动",
            "spanish": "Interacción contractual"
        },
        "external": {
            "english": "External",
            "german": "Extern",
            "japanese": "外部",
            "korean": "외부",
            "mandarin": "外部",
            "spanish": "Externo"
        },
        "externalTransaction": {
            "english": "External transaction",
            "german": "Externe Transaktion",
            "japanese": "外部取引",
            "korean": "외부 트랜잭션",
            "mandarin": "对外交易",
            "spanish": "Transacción externa"
        },
        "from": {
            "english": "from",
            "german": "von",
            "japanese": "から",
            "korean": "에서",
            "mandarin": "从",
            "spanish": "de"
        },
        "headerAmount": {
            "english": "Amount",
            "german": "Menge",
            "japanese": "量",
            "korean": "양",
            "mandarin": "量",
            "spanish": "Cantidad"
        },
        "headerDate": {
            "english": "Date",
            "german": "Datum",
            "japanese": "日付",
            "korean": "날짜",
            "mandarin": "日期",
            "spanish": "Fecha"
        },
        "headerFrom": {
            "english": "From",
            "german": "Von",
            "japanese": "から",
            "korean": "에서",
            "mandarin": "从",
            "spanish": "De"
        },
        "headerStatus": {
            "english": "Status",
            "german": "Status",
            "japanese": "状態",
            "korean": "상태",
            "mandarin": "状态",
            "spanish": "Estado"
        },
        "headerTo": {
            "english": "To",
            "german": "Zu",
            "japanese": "に",
            "korean": "에",
            "mandarin": "至",
            "spanish": "A"
        },
        "headerTransaction": {
            "english": "Transaction",
            "german": "Transaktion",
            "japanese": "トランザクション",
            "korean": "트랜잭션",
            "mandarin": "交易",
            "spanish": "Transacción"
        },
        "lastOneMonth": {
            "english": "Last 1 month",
            "german": "Letzten 1 Monat",
            "japanese": "過去1か月",
            "korean": "지난 1개월",
            "mandarin": "最近1个月",
            "spanish": "Último mes"
        },
        "lastOneWeek": {
            "english": "Last 1 week",
            "german": "Letzte 1 Woche",
            "japanese": "過去1週間",
            "korean": "지난 1주",
            "mandarin": "最近1周",
            "spanish": "Última semana"
        },
        "lastSixMonts": {
            "english": "Last 6 months",
            "german": "Letzte 6 Monate",
            "japanese": "過去6か月",
            "korean": "지난 6개월",
            "mandarin": "最近6个月",
            "spanish": "Últimos 6 meses"
        },
        "loading": {
            "english": "Loading",
            "german": "Wird geladen",
            "japanese": "読み込み中",
            "korean": "로딩",
            "mandarin": "载入中",
            "spanish": "Cargando"
        },
        "netword": {
            "english": "Network",
            "german": "Netzwerk",
            "japanese": "ネットワーク",
            "korean": "네트워크",
            "mandarin": "网络",
            "spanish": "Red"
        },
        "network": {
            "english": "Network",
            "german": "Netzwerk",
            "japanese": "通信網",
            "korean": "네트워크",
            "mandarin": "网络",
            "spanish": "Red"
        },
        "noTransaction": {
            "english": "No Transaction Activity",
            "german": "Keine Transaktionsaktivität",
            "japanese": "トランザクション履歴なし",
            "korean": "트랜잭션 활동이 없습니다",
            "mandarin": "没有交易活动",
            "spanish": "Sin actividad de transacción"
        },
        "pending": {
            "english": "Pending",
            "german": "steht aus",
            "japanese": "保留中",
            "korean": "대기 중",
            "mandarin": "待定",
            "spanish": "Pendiente"
        },
        "rate": {
            "english": "Rate",
            "german": "Bewertung",
            "japanese": "割合",
            "korean": "비율",
            "mandarin": "率",
            "spanish": "Velocidad"
        },
        "receive": {
            "english": "Receive",
            "german": "Erhalten",
            "japanese": "受け取る",
            "korean": "받기",
            "mandarin": "接收",
            "spanish": "Recibir"
        },
        "received": {
            "english": "Received",
            "german": "Empfangen",
            "japanese": "受信済",
            "korean": "받음",
            "mandarin": "已收到",
            "spanish": "Recibido"
        },
        "receiveFrom": {
            "english": "Receive from",
            "german": "Erhalten von",
            "japanese": "から受信",
            "korean": "수신",
            "mandarin": "收到",
            "spanish": "Recibir de"
        },
        "send": {
            "english": "Send",
            "german": "Senden",
            "japanese": "送る",
            "korean": "보내다",
            "mandarin": "发送",
            "spanish": "Enviar"
        },
        "sendTo": {
            "english": "Send to",
            "german": "Senden an",
            "japanese": "に送る",
            "korean": "보내기",
            "mandarin": "发给",
            "spanish": "Enviar a"
        },
        "sent": {
            "english": "Sent",
            "german": "Geschickt",
            "japanese": "送信済",
            "korean": "보냄",
            "mandarin": "已发送",
            "spanish": "Expedido"
        },
        "startedAt": {
            "english": "Started at",
            "german": "Begonnen um",
            "japanese": "で開始",
            "korean": "에 시작",
            "mandarin": "开始于",
            "spanish": "Empezó a las"
        },
        "successful": {
            "english": "Successful",
            "german": "Erfolgreich",
            "japanese": "成功した",
            "korean": "성공한",
            "mandarin": "成功",
            "spanish": "Exitoso"
        },
        "to": {
            "english": "to",
            "german": "zu",
            "japanese": "に",
            "korean": "에",
            "mandarin": "至",
            "spanish": "a"
        },
        "topup": {
            "english": "Topup",
            "german": "Aufladen",
            "japanese": "チャージ",
            "korean": "충전",
            "mandarin": "充值",
            "spanish": "Recarga"
        },
        "transactionActivities": {
            "english": "Transaction Activities",
            "german": "Transaktionsaktivitäten",
            "japanese": "トランザクション履歴",
            "korean": "트랜잭션 활동",
            "mandarin": "交易活动",
            "spanish": "Actividades de transacción"
        },
        "unavailable": {
            "english": "Unavailable",
            "german": "Nicht verfügbar",
            "japanese": "利用できません",
            "korean": "불가능",
            "mandarin": "不可用",
            "spanish": "No disponible"
        },
        "unsuccessful": {
            "english": "Unsuccessful",
            "german": "Erfolglos",
            "japanese": "失敗した",
            "korean": "실패",
            "mandarin": "不成功",
            "spanish": "Fracasado"
        },
        "viewEtherscan": {
            "english": "View On Etherscan",
            "german": "Blick auf Etherscan",
            "japanese": "Etherscanで表示",
            "korean": "Etherscan에서 보기",
            "mandarin": "Etherscan查寻",
            "spanish": "Ver en Etherscan"
        },
        "viewMore": {
            "english": "View more",
            "german": "Mehr sehen",
            "japanese": "もっと見る",
            "korean": "더보기",
            "mandarin": "查看更多",
            "spanish": "Ver más"
        },
        "viewOnEtherscan": {
            "english": "View On Etherscan",
            "german": "Blick auf Etherscan",
            "japanese": "Etherscanで確認",
            "korean": "Etherscan에서 보기",
            "mandarin": "在Etherscan上查看",
            "spanish": "Ver en Etherscan"
        }
    }
}